another_expect/ExpectFailedError.py
another_expect/__init__.py
another_expect/_vendor/__init__.py
another_expect/_vendor/ordered_set-3.1.1.dist-info/INSTALLER
another_expect/_vendor/ordered_set-3.1.1.dist-info/METADATA
another_expect/_vendor/ordered_set-3.1.1.dist-info/MIT-LICENSE
another_expect/_vendor/ordered_set-3.1.1.dist-info/RECORD
another_expect/_vendor/ordered_set-3.1.1.dist-info/WHEEL
another_expect/_vendor/ordered_set-3.1.1.dist-info/top_level.txt
another_expect/_vendor/ordered_set.py
another_expect/_vendor/simple_chalk/__init__.py
another_expect/_vendor/simple_chalk/src/Style.py
another_expect/_vendor/simple_chalk/src/__init__.py
another_expect/_vendor/simple_chalk/src/data.py
another_expect/_vendor/simple_chalk/src/makeAChalkClass.py
another_expect/_vendor/simple_chalk/src/makeAChalkInstance.py
another_expect/_vendor/simple_chalk/src/makeChalkHelpers.py
another_expect/_vendor/simple_chalk/src/utils/__init__.py
another_expect/_vendor/simple_chalk/src/utils/append.py
another_expect/_vendor/simple_chalk/src/utils/appendAll.py
another_expect/_vendor/simple_chalk/src/utils/assignMissing.py
another_expect/_vendor/simple_chalk/src/utils/flatten.py
another_expect/_vendor/simple_chalk/src/utils/forEach.py
another_expect/_vendor/simple_chalk/src/utils/get.py
another_expect/_vendor/simple_chalk/src/utils/getAttributeKeys.py
another_expect/_vendor/simple_chalk/src/utils/internal/__init__.py
another_expect/_vendor/simple_chalk/src/utils/internal/getFnSignature.py
another_expect/_vendor/simple_chalk/src/utils/internal/getNumPositionalParams.py
another_expect/_vendor/simple_chalk/src/utils/internal/getTypedResult.py
another_expect/_vendor/simple_chalk/src/utils/internal/makeCallFn.py
another_expect/_vendor/simple_chalk/src/utils/internal/validateStr.py
another_expect/_vendor/simple_chalk/src/utils/invoke.py
another_expect/_vendor/simple_chalk/src/utils/invokeAttr.py
another_expect/_vendor/simple_chalk/src/utils/isEmpty.py
another_expect/_vendor/simple_chalk/src/utils/isLaden.py
another_expect/_vendor/simple_chalk/src/utils/isSomething.py
another_expect/_vendor/simple_chalk/src/utils/isTruthy.py
another_expect/_vendor/simple_chalk/src/utils/join.py
another_expect/_vendor/simple_chalk/src/utils/keepWhen.py
another_expect/_vendor/simple_chalk/src/utils/lowerFirst.py
another_expect/_vendor/simple_chalk/src/utils/mMap.py
another_expect/_vendor/simple_chalk-0.1.0.dist-info/INSTALLER
another_expect/_vendor/simple_chalk-0.1.0.dist-info/METADATA
another_expect/_vendor/simple_chalk-0.1.0.dist-info/RECORD
another_expect/_vendor/simple_chalk-0.1.0.dist-info/WHEEL
another_expect/_vendor/simple_chalk-0.1.0.dist-info/top_level.txt
another_expect/_vendor/tedent/_vendor/ordered_set-3.1.1-py3.7.egg-info/PKG-INFO
another_expect/_vendor/tedent/_vendor/ordered_set-3.1.1-py3.7.egg-info/SOURCES.txt
another_expect/_vendor/tedent/_vendor/ordered_set-3.1.1-py3.7.egg-info/dependency_links.txt
another_expect/_vendor/tedent/_vendor/ordered_set-3.1.1-py3.7.egg-info/installed-files.txt
another_expect/_vendor/tedent/_vendor/ordered_set-3.1.1-py3.7.egg-info/top_level.txt
another_expect/_vendor/tedent/_vendor/wrapt-1.11.1.dist-info/INSTALLER
another_expect/_vendor/tedent/_vendor/wrapt-1.11.1.dist-info/LICENSE
another_expect/_vendor/tedent/_vendor/wrapt-1.11.1.dist-info/METADATA
another_expect/_vendor/tedent/_vendor/wrapt-1.11.1.dist-info/RECORD
another_expect/_vendor/tedent/_vendor/wrapt-1.11.1.dist-info/WHEEL
another_expect/_vendor/tedent/_vendor/wrapt-1.11.1.dist-info/top_level.txt
another_expect/_vendor/tedent-0.1.5.dist-info/INSTALLER
another_expect/_vendor/tedent-0.1.5.dist-info/METADATA
another_expect/_vendor/tedent-0.1.5.dist-info/RECORD
another_expect/_vendor/tedent-0.1.5.dist-info/WHEEL
another_expect/_vendor/tedent-0.1.5.dist-info/top_level.txt
another_expect/_vendor/wrapt-1.11.1.dist-info/INSTALLER
another_expect/_vendor/wrapt-1.11.1.dist-info/LICENSE
another_expect/_vendor/wrapt-1.11.1.dist-info/METADATA
another_expect/_vendor/wrapt-1.11.1.dist-info/RECORD
another_expect/_vendor/wrapt-1.11.1.dist-info/WHEEL
another_expect/_vendor/wrapt-1.11.1.dist-info/top_level.txt
another_expect-0.1.1.dist-info/WHEEL
another_expect-0.1.1.dist-info/METADATA
another_expect-0.1.1.dist-info/RECORD
