Metadata-Version: 2.1
Name: another-expect
Version: 0.1.1
Summary: An expect function with an api and documentation to my liking
Home-page: https://github.com/olsonpm/py_simple-test
Author: Philip Olson
Author-email: philip.olson@pm.me
Requires-Python: >=3.7,<4.0
Classifier: Programming Language :: Python :: 3
Classifier: Programming Language :: Python :: 3.7
Project-URL: Repository, https://github.com/olsonpm/py_simple-test
